{
  "_说明": "Yatori Android 远程策略 JSON。本文件用于控制公告、版本提示和下载地址。",
  "schemaVersion": 1,
  "_enabled说明": "是否启用远程策略。true=启用，false=客户端忽略本策略。",
  "enabled": true,
  "_minSupportedVersion说明": "低于此版本时提示升级。",
  "minSupportedVersion": "0.3.7",
  "_latestVersion说明": "当前最新版本号。",
  "latestVersion": "0.3.9",
  "_forceUpdate说明": "是否强制更新。true=必须更新后使用，false=仅提示。",
  "forceUpdate": false,
  "_softUpdate说明": "是否显示普通更新提示。",
  "softUpdate": true,
  "_message说明": "更新提示文案。",
  "message": "发现新版本，请前往 GitHub Releases 下载最新版。",
  "_disabledMessage说明": "远程禁用时显示的提示。",
  "disabledMessage": "当前版本已停用，请前往 GitHub 下载最新版。",
  "_downloadUrl说明": "最新版下载地址。",
  "downloadUrl": "https://github.com/yuanglove/yatori-go-android/releases/latest",
  "_updatedAt说明": "策略更新时间。",
  "updatedAt": "2026-07-07 22:50:00"
}
